{"ProjectBreakpoints":"{\"Value\":{\"Framework/GetTransactionData.xaml\":[{\"ConditionalExpression\":null,\"ActionExpression\":null,\"ExpectedHitCounter\":null,\"ShouldContinueAfterAction\":false,\"IsEnabled\":true,\"ActivityIdRef\":\"Assign_7\",\"ActivityId\":\"1.11\",\"ActivityName\":\"Assign out_TransactionField2\"}]}}","OpenedDocuments":"[\"Framework/GetAppCredentials.xaml\",\"Main.xaml\"]","ProjectWatches":"{\"Value\":[]}","LibraryProjectSettings":"{\"IncludeSourcesByDefault\":true,\"UseCSharpCompiler\":false,\"DefaultActivitiesRootCategories\":[null]}"}